[
    {
        "question": "1.   Which shape appears in all the diagrams?",
        "options": [
            "A triangle          B   square          C   pentagon          D   hexagon          E   star"
        ],
        "answer": null
    },
    {
        "question": "2.   How many even numbers are there between 27 and 43?",
        "options": [
            "A 5",
            "B 6",
            "C 7",
            "D 8",
            "E 15"
        ],
        "answer": null
    },
    {
        "question": "3.\t What is the smallest number that has a remainder of 1 when divided by 2, 3 or 4? First Mathematics Challenge",
        "options": [
            "A 5",
            "B 7",
            "C 11",
            "D 13",
            "E 25"
        ],
        "answer": null
    },
    {
        "question": "4. \t A manager of a football team, Milo Mastery, needs to choose a new kit. There are 3 colours of shirt.  Purple, red and yellow. There are 2 colours for shorts.  Blue and black. How many different combinations of shirts and shorts can he make?",
        "options": [
            "A 2",
            "B 3",
            "C 4",
            "D 5",
            "E 6"
        ],
        "answer": null
    },
    {
        "question": "5.\t A pizza is divided into equal slices. How many slices have been taken?",
        "options": [
            "A 4",
            "B 3",
            "C 5",
            "D 6",
            "E 7"
        ],
        "answer": null
    },
    {
        "question": "6.   What should replace the question mark to make the calculation correct? B   -1 C   -2 D   -3 E   -5 4 8 5 x2 ? +2 First Mathematics Challenge",
        "options": [
            "A x1"
        ],
        "answer": null
    },
    {
        "question": "7.\t A two-digit number is less than 50. The sum of the digits is 12 and the difference between them is 4. What is the number?",
        "options": [
            "A 15",
            "B 26",
            "C 39",
            "D 48",
            "E 84"
        ],
        "answer": null
    },
    {
        "question": "8.\t \t How many triangles are in the diagram?",
        "options": [
            "A 5",
            "B 7",
            "C 11",
            "D 13",
            "E 25"
        ],
        "answer": null
    },
    {
        "question": "9.\t Farhat, Jess and Tom have 18 apples between them. Farhat has half the number of apples that Tom has. Jess has three times the number of apples that Tom has. How many apples does Tom have? First Mathematics Challenge",
        "options": [
            "A 2",
            "B 3",
            "C 4",
            "D 5",
            "E 6"
        ],
        "answer": null
    },
    {
        "question": "10.\t\t DanDan Double likes to multiply whole numbers by two. He realised that his answers are:",
        "options": [
            "A always odd          B   always even          C   sometimes odd",
            "D sometimes even          E   always less than 100"
        ],
        "answer": null
    },
    {
        "question": "11. \t Pencils can be bought in packs of 8. There are 28 pupils in class. How many packs must the teacher buy to be sure that everyone gets a pencil of their own?",
        "options": [
            "A 2",
            "B 3",
            "C 4",
            "D 5",
            "E 6"
        ],
        "answer": null
    },
    {
        "question": "12.   In the calculations below, which number is hidden by the       ? 3 +     = 8 +     = 14 First Mathematics Challenge",
        "options": [
            "A 6",
            "B 7",
            "C 8",
            "D 9",
            "E 10"
        ],
        "answer": null
    },
    {
        "question": "13.\t\t Tan is knitting a scarf in a week. At the end of Monday his scarf measures 68cm. He knits another 5cm every day. How long is it at the end of Friday?",
        "options": [
            "A 72cm",
            "B 73cm",
            "C 78cm",
            "D 83cm",
            "E 88cm"
        ],
        "answer": null
    },
    {
        "question": "14.\t\t Maya Makealot can build this set of 3 stairs with 12 blocks. How many blocks will she need to build a set of 6 stairs?",
        "options": [
            "A 42",
            "B 30",
            "C 36",
            "D 21",
            "E 52"
        ],
        "answer": null
    },
    {
        "question": "15.  \t Amanda has 10 coins in her purse. They are 2p and 5p coins. The coins make 32p in total. How many 5p coins are there in Amanda’s purse? First Mathematics Challenge",
        "options": [
            "A 3",
            "B 4",
            "C 5",
            "D 6",
            "E 7"
        ],
        "answer": null
    },
    {
        "question": "16.\t\t Bethany’s water bottle holds 150ml when it is three quarters full. How much does it hold when it is one quarter full?",
        "options": [
            "A 15 ml",
            "B 50ml",
            "C 200ml",
            "D 450ml",
            "E 600ml"
        ],
        "answer": null
    },
    {
        "question": "17.\t\t The clock in the school staffroom is always 5 minutes slow. However, Mr. Punctual’s watch is always 8 minutes fast. The staffroom clock is showing 11.30am. What time is shown on Mr. Punctual’s watch?",
        "options": [
            "A 11.17am        B   11.27am        C   11.33am        D   11.35am        E   11.43am"
        ],
        "answer": null
    },
    {
        "question": "18.\t\t There are 9 cones along a fun run course. The first one marks the start of the race and the last one is at the finish line. The distance between each cone is 7 metres. How long is the fun run? First Mathematics Challenge",
        "options": [
            "A 56 metres       B   72 metres        C   54 metres       D   49 metres       E   63 metres"
        ],
        "answer": null
    },
    {
        "question": "19. \t On the planet Numeros, the natives have a special sort of mathematics using the symbol 2     3 means add 2 and 3 and then add on the product of 2 and 3 In this example 2     3 would equal 11. What is 5     6?",
        "options": [
            "A 11",
            "B 19",
            "C 30",
            "D 41",
            "E 330"
        ],
        "answer": null
    },
    {
        "question": "20.\t\t In the diagram, a square is divided into 9 equal squares. What fraction of the big square is shaded? 6 4 3 2 9 © First Mathematics Challenge 2020 First Mathematics Challenge",
        "options": [
            "A 1",
            "B 1",
            "C 1",
            "D 1",
            "E 2"
        ],
        "answer": null
    }
]